bbs/__init__.py
bbs/shell/__init__.py
bbs/shell/usage.py
bbs/src/temp.txt
package_name/__init__.py
package_name/shell/__init__.py
package_name/shell/usage.py
package_name/src/temp.txt
bbs-0.0.1.dist-info/LICENSE
bbs-0.0.1.dist-info/METADATA
bbs-0.0.1.dist-info/WHEEL
bbs-0.0.1.dist-info/entry_points.txt
bbs-0.0.1.dist-info/top_level.txt
bbs-0.0.1.dist-info/zip-safe
bbs-0.0.1.dist-info/RECORD
